Metadata-Version: 2.1
Name: kurumiiexedebug
Version: 1.4.2
Summary: A handy litle tool
Home-page: UNKNOWN
Author: Kurumii
License: UNKNOWN
Platform: UNKNOWN
